bSuite/auth/__init__.py
bSuite/auth/client.py
bSuite/auth/etc.py
bSuite/auth/middleware.py
bSuite/configure/__init__.py
bSuite/configure/configure.py
bSuite/database/__init__.py
bSuite/database/base.py
bSuite/database/crypto.py
bSuite/database/mapped.py
bSuite/database/models.py
bSuite/utils/__init__.py
bSuite/utils/spotify.py
bSuite/utils/storage.py
bSuite/utils/strings.py
bSuite/utils/time.py
bSuite_python-3.2.0.dist-info/LICENSE
bSuite_python-3.2.0.dist-info/METADATA
bSuite_python-3.2.0.dist-info/WHEEL
bSuite_python-3.2.0.dist-info/top_level.txt
bSuite_python-3.2.0.dist-info/RECORD
