Metadata-Version: 2.1
Name: bSuite-python
Version: 3.2.0
Summary: advanced helper modules. python edition
Author-email: John Birdwell <j.c.birdwell@gmail.com>
License: GNU GENERAL PUBLIC LICENSE
Project-URL: Repository, https://github.com/jcbirdwell/bSuite
Keywords: configs,utilities,database,postgres,authentication
Classifier: Development Status :: 3 - Alpha
Requires-Python: >=3.10
License-File: LICENSE
Requires-Dist: psycopg[pool]
Requires-Dist: tekore
Requires-Dist: httpx
Requires-Dist: browser-cookie3
Requires-Dist: requests
Requires-Dist: fastapi
Requires-Dist: starlette
Requires-Dist: cryptography
